django_bootstrap3_multidatepicker/__init__.py
django_bootstrap3_multidatepicker/manage.py
django_bootstrap3_multidatepicker/django_bootstrap3_multidatepicker/__init__.py
django_bootstrap3_multidatepicker/django_bootstrap3_multidatepicker/collect_datepicker_trans.py
django_bootstrap3_multidatepicker/django_bootstrap3_multidatepicker/fields.py
django_bootstrap3_multidatepicker/django_bootstrap3_multidatepicker/settings.py
django_bootstrap3_multidatepicker/django_bootstrap3_multidatepicker/urls.py
django_bootstrap3_multidatepicker/django_bootstrap3_multidatepicker/widgets.py
django_bootstrap3_multidatepicker/django_bootstrap3_multidatepicker/wsgi.py
django_bootstrap3_multidatepicker/django_bootstrap3_multidatepicker/static/django_bootstrap3_multidatepicker/bootstrap-datepicker.min.js
django_bootstrap3_multidatepicker/django_bootstrap3_multidatepicker/static/django_bootstrap3_multidatepicker/bootstrap-datepicker3.standalone.css
django_bootstrap3_multidatepicker/django_bootstrap3_multidatepicker/static/django_bootstrap3_multidatepicker/bootstrap-datepicker3.standalone.min.css
django_bootstrap3_multidatepicker/django_bootstrap3_multidatepicker/static/django_bootstrap3_multidatepicker/date.format.min.js
django_bootstrap3_multidatepicker/django_bootstrap3_multidatepicker/static/django_bootstrap3_multidatepicker/django-datepicker.js
django_bootstrap3_multidatepicker/django_bootstrap3_multidatepicker/static/django_bootstrap3_multidatepicker/django-datepicker.min.js
django_bootstrap3_multidatepicker/django_bootstrap3_multidatepicker/static/django_bootstrap3_multidatepicker/datepicker_locales/bootstrap-datepicker.ar.min.js
django_bootstrap3_multidatepicker/django_bootstrap3_multidatepicker/static/django_bootstrap3_multidatepicker/datepicker_locales/bootstrap-datepicker.az.min.js
django_bootstrap3_multidatepicker/django_bootstrap3_multidatepicker/static/django_bootstrap3_multidatepicker/datepicker_locales/bootstrap-datepicker.bg.min.js
django_bootstrap3_multidatepicker-0.1.5.dist-info/DESCRIPTION.rst
django_bootstrap3_multidatepicker-0.1.5.dist-info/METADATA
django_bootstrap3_multidatepicker-0.1.5.dist-info/RECORD
django_bootstrap3_multidatepicker-0.1.5.dist-info/WHEEL
django_bootstrap3_multidatepicker-0.1.5.dist-info/metadata.json
django_bootstrap3_multidatepicker-0.1.5.dist-info/top_level.txt
