Metadata-Version: 2.0
Name: django-bootstrap3-multidatepicker
Version: 0.1.5
Summary: Datepicker that supports the selection of multiple dates for Django, using Bootstrap Twitter.
Home-page: https://github.com/FabianWe/django-bootstrap3-multidatepicker
Author: Fabian Wenzelmann
Author-email: fabianwenzelmann@posteo.de
License: Apache License 2.0
Keywords: django calendar multidate
Platform: UNKNOWN
Classifier: Development Status :: 4 - Beta
Classifier: License :: OSI Approved :: Apache Software License
Classifier: Programming Language :: Python
Classifier: Programming Language :: Python :: 3 :: Only
Classifier: Operating System :: OS Independent
Classifier: Environment :: Web Environment
Classifier: Topic :: Software Development :: Libraries :: Python Modules
Classifier: Framework :: Django :: 1.9
Classifier: Framework :: Django
Classifier: Intended Audience :: Developers
Requires-Dist: Django
Requires-Dist: django-bootstrap3
